RobotframeworkExtensions/Collection.py
RobotframeworkExtensions/RobotframeworkExtensions.pdf
RobotframeworkExtensions/__init__.py
RobotframeworkExtensions/version.py
robotframework_extensions_collection-0.10.0.dist-info/LICENSE
robotframework_extensions_collection-0.10.0.dist-info/METADATA
robotframework_extensions_collection-0.10.0.dist-info/WHEEL
robotframework_extensions_collection-0.10.0.dist-info/top_level.txt
robotframework_extensions_collection-0.10.0.dist-info/RECORD
